setup.py
PyODConverter/__init__.py
PyODConverter/tests.py
PyODConverter.egg-info/PKG-INFO
PyODConverter.egg-info/SOURCES.txt
PyODConverter.egg-info/dependency_links.txt
PyODConverter.egg-info/top_level.txt