Metadata-Version: 1.1
Name: PyODConverter
Version: 1.7
Summary: Python package to automate document conversions using LibreOffice/OpenOffice.org
Home-page: https://github.com/dieselpoweredkitten/pyodconverter
Author: PyODConverter contributors
Author-email: me@require.pm
License: GPL v3
Platform: All
Classifier: Intended Audience :: Developers
Classifier: Development Status :: 3 - Alpha
Classifier: Operating System :: OS Independent
Classifier: Programming Language :: Python
Classifier: Programming Language :: Python :: 2.7
Classifier: Programming Language :: Python :: 3.3
